main_imports/Extensions.py
main_imports/__init__.py
main_imports/file1.py
main_imports/log.py
main_imports/validtors.py
main_imports/extras/__init__.py
main_imports/extras/empty.py
main_imports-1.0.1.dist-info/METADATA
main_imports-1.0.1.dist-info/WHEEL
main_imports-1.0.1.dist-info/top_level.txt
main_imports-1.0.1.dist-info/RECORD
