Metadata-Version: 2.1
Name: main-imports
Version: 1.0.1
Summary: Read 
Author: Fahmy
Author-email: Fahmy@realpython.com
License: MIT
Platform: UNKNOWN
Classifier: License :: OSI Approved :: MIT License
Classifier: Programming Language :: Python :: 3
Classifier: Programming Language :: Python :: 3.7
